LICENSE
README.md
setup.cfg
setup.py
ijim/__init__.py
ijim/comparable.py
ijim/exceptions.py
ijim/interval_map.py
ijim/main.py
ijim/utils.py
ijim.egg-info/PKG-INFO
ijim.egg-info/SOURCES.txt
ijim.egg-info/dependency_links.txt
ijim.egg-info/top_level.txt