Metadata-Version: 2.1
Name: ijim
Version: 0.0.4
Summary: interval map
Home-page: https://github.com/eightlay/IntervalMap
Author-email: timurdzhalalov@yahoo.com
License-File: LICENSE
